{
  "محمد بن عبد الله": {
    "short": "رسول الله صلى الله عليه وسلم وخاتم الأنبياء.",
    "full": "بعث في مكة ثم هاجر إلى المدينة وأسس دولة الإسلام، وتوفي سنة 11 هـ.",
    "img": "persons/default.png"
  },
  "حمزة بن عبد المطلب": {
    "short": "أسد الله وأسد رسوله، استشهد يوم أحد.",
    "full": "هو حمزة بن عبد المطلب الهاشمي القرشي، عم رسول الله صلى الله عليه وسلم وأخوه من الرضاعة، أسلم في مكة وشهد بدرًا وأُحدًا.",
    "img": "persons/default.png"
  },
  "مصعب بن عمير": {
    "short": "أول سفير في الإسلام وحامل لواء أحد.",
    "full": "مصعب بن عمير بن هاشم من السابقين إلى الإسلام، بعثه النبي صلى الله عليه وسلم داعية إلى المدينة واستشهد يوم أحد.",
    "img": "persons/default.png"
  }
}
